nightskycam/__init__.py
nightskycam/aperture/runner.py
nightskycam/asicams/__init__.py
nightskycam/asicams/camera.py
nightskycam/asicams/runner.py
nightskycam/cams/__init__.py
nightskycam/cams/camera.py
nightskycam/cams/runner.py
nightskycam/cams/utils.py
nightskycam/commands/__init__.py
nightskycam/commands/runner.py
nightskycam/config_update/__init__.py
nightskycam/config_update/runner.py
nightskycam/dummycams/__init__.py
nightskycam/dummycams/camera.py
nightskycam/dummycams/runner.py
nightskycam/ftp/__init__.py
nightskycam/ftp/runner.py
nightskycam/introspection/__init__.py
nightskycam/location_info/__init__.py
nightskycam/location_info/ip.py
nightskycam/location_info/runner.py
nightskycam/main.py
nightskycam/process/__init__.py
nightskycam/process/bits_conversion.py
nightskycam/process/darkframes.py
nightskycam/process/debayer.py
nightskycam/process/resize.py
nightskycam/process/runner.py
nightskycam/process/stretch.py
nightskycam/py.typed
nightskycam/ref.py
nightskycam/sleepypi/__init__.py
nightskycam/sleepypi/runner.py
nightskycam/space_keeper/__init__.py
nightskycam/space_keeper/runner.py
nightskycam/space_keeper/utils.py
nightskycam/status/__init__.py
nightskycam/status/runner.py
nightskycam/tests/__init__.py
nightskycam/tests/runner.py
nightskycam/usbcams/__init__.py
nightskycam/usbcams/camera.py
nightskycam/usbcams/runner.py
nightskycam/utils/__init__.py
nightskycam/utils/commands.py
nightskycam/utils/file_saving.py
nightskycam/utils/filename.py
nightskycam/utils/folder_stats.py
nightskycam/utils/formating.py
nightskycam/utils/ftp.py
nightskycam/utils/location_info.py
nightskycam/utils/night.py
nightskycam/utils/py.typed
nightskycam/utils/test_utils.py
nightskycam/utils/weather.py
nightskycam/utils/websocket_manager.py
nightskycam/version.py
nightskycam-0.1.23.dist-info/METADATA
nightskycam-0.1.23.dist-info/WHEEL
nightskycam-0.1.23.dist-info/entry_points.txt
nightskycam-0.1.23.dist-info/RECORD
