Metadata-Version: 2.4
Name: nightskycam
Version: 0.1.23
Summary: taking pictures at night
Author: Vincent Berenz
Author-email: vberenz@tuebingen.mpg.de
Requires-Python: >=3.12,<3.14
Classifier: Programming Language :: Python :: 3
Classifier: Programming Language :: Python :: 3.12
Classifier: Programming Language :: Python :: 3.13
Requires-Dist: astropy (>=7.2.0,<8.0.0)
Requires-Dist: auto-stretch (>=0.0.3,<0.0.4)
Requires-Dist: cachetools (>=6.2.2,<7.0.0)
Requires-Dist: h5darkframes (>=0.1.7,<0.2.0)
Requires-Dist: matplotlib (>=3.10.7,<4.0.0)
Requires-Dist: netifaces (>=0.11.0,<0.12.0)
Requires-Dist: nightskycam-focus (>=0.1.9,<0.2.0)
Requires-Dist: nightskycam-serialization (>=0.1.4,<0.2.0)
Requires-Dist: psutil (>=7.1.3,<8.0.0)
Requires-Dist: pyephem (>=9.99,<10.0)
Requires-Dist: pyftpdlib (>=2.1.0,<3.0.0)
Requires-Dist: pyusb (>=1.3.1,<2.0.0)
Requires-Dist: requests (>=2.32.5,<3.0.0)
Requires-Dist: websocket-client (>=1.9.0,<2.0.0)
Requires-Dist: websocket-server (>=0.6.4,<0.7.0)
